[
  {
    "url": "https://www.impressiondigital.com/blog/digital-marketing-glossary/",
    "category": "Terminology",
    "description": "Digital marketing glossary",
    "priority": 1
  },
  {
    "url": "https://www.marketingterms.com/glossary/",
    "category": "Terminology",
    "description": "Marketing terms glossary",
    "priority": 1
  },
  {
    "url": "https://www.mtu.edu/umc/services/websites/terminology/",
    "category": "Terminology",
    "description": "Website terminology",
    "priority": 1
  },
  {
    "url": "https://supermetrics.com/blog/how-to-analyze-campaigns",
    "category": "Campaign Analytics",
    "description": "How to analyze campaigns",
    "priority": 1
  },
  {
    "url": "https://improvado.io/blog/campaign-analytics",
    "category": "Campaign Analytics",
    "description": "Campaign analytics guide",
    "priority": 1
  },
  {
    "url": "https://supermetrics.com/blog/growth-marketing-analytics",
    "category": "Campaign Analytics",
    "description": "Growth marketing analytics",
    "priority": 1
  },
  {
    "url": "https://supermetrics.com/blog/marketing-data-management",
    "category": "Campaign Analytics",
    "description": "Marketing data management",
    "priority": 1
  },
  {
    "url": "https://www.dashthis.com/kpi-examples/",
    "category": "KPIs",
    "description": "Ultimate KPI examples guide",
    "priority": 1
  },
  {
    "url": "https://www.klipfolio.com/resources/kpi-examples/digital-marketing",
    "category": "KPIs",
    "description": "Digital marketing KPI examples",
    "priority": 1
  },
  {
    "url": "https://www.simplekpi.com/Resources/Articles/what-are-kpis",
    "category": "KPIs",
    "description": "What are KPIs",
    "priority": 1
  },
  {
    "url": "https://advertising.amazon.com/library/guides/marketing-funnel",
    "category": "Funnel",
    "description": "Marketing funnel guide",
    "priority": 1
  },
  {
    "url": "https://www.semrush.com/blog/marketing-funnel/",
    "category": "Funnel",
    "description": "Marketing funnel stages",
    "priority": 1
  },
  {
    "url": "https://analyticsliv.com/blogs/dv360-campaign-structure-best-practices",
    "category": "Hierarchy",
    "description": "DV360 campaign structure",
    "priority": 1
  },
  {
    "url": "https://blog.adnabu.com/google-ads/google-ads-reporting/",
    "category": "Hierarchy",
    "description": "Google Ads reporting",
    "priority": 1
  },
  {
    "url": "https://www.factors.ai/blog/google-ads-101-types-benefits",
    "category": "Google Ads",
    "description": "Google Ads 101",
    "priority": 1
  },
  {
    "url": "https://www.semrush.com/blog/search-engine-marketing/",
    "category": "SEM",
    "description": "Search engine marketing",
    "priority": 1
  },
  {
    "url": "https://zapier.com/blog/types-of-google-ads/",
    "category": "Google Ads",
    "description": "Types of Google Ads - Zapier",
    "priority": 1
  },
  {
    "url": "https://www.demandcurve.com/blog/types-of-google-ads",
    "category": "Google Ads",
    "description": "Types of Google Ads - Demand Curve",
    "priority": 1
  },
  {
    "url": "https://support.google.com/google-ads/answer/2580383?hl=en",
    "category": "Google Ads",
    "description": "Google Ads Help",
    "priority": 1
  },
  {
    "url": "https://www.technadigital.com/bing-ads-effective-campaign-guide/",
    "category": "Bing Ads",
    "description": "Bing Ads campaign guide",
    "priority": 1
  },
  {
    "url": "https://www.datafeedwatch.com/blog/microsoft-bing-ads-guide",
    "category": "Bing Ads",
    "description": "Microsoft Bing Ads guide",
    "priority": 1
  },
  {
    "url": "https://magicbrief.com/post/understanding-meta-ads-reporting-a-complete-guide",
    "category": "Meta Ads",
    "description": "Meta Ads reporting guide",
    "priority": 1
  },
  {
    "url": "https://leadsbridge.com/blog/what-are-meta-ads/",
    "category": "Meta Ads",
    "description": "What are Meta Ads",
    "priority": 1
  },
  {
    "url": "https://support.agorapulse.com/en/articles/10137532-meta-ads-report-explained",
    "category": "Meta Ads",
    "description": "Meta Ads report explained",
    "priority": 1
  },
  {
    "url": "https://www.facebook.com/business/help/1153577308409919?id=1858550721111595",
    "category": "Meta Ads",
    "description": "Facebook audience targeting",
    "priority": 1
  },
  {
    "url": "https://www.sprinklr.com/help/articles/getting-started/linkedin-ads-campaign-structure-roles/645234780d27fc559bbe4b62",
    "category": "LinkedIn",
    "description": "LinkedIn Ads structure",
    "priority": 1
  },
  {
    "url": "https://www.linkedin.com/help/lms/answer/a424171",
    "category": "LinkedIn",
    "description": "LinkedIn Ads targeting",
    "priority": 1
  },
  {
    "url": "https://digitalbrolly.com/social-media-platforms-for-marketing/",
    "category": "Social",
    "description": "Social media platforms",
    "priority": 1
  },
  {
    "url": "https://www.singlegrain.com/blog/ms/best-social-media-platforms-for-advertising/",
    "category": "Social",
    "description": "Best social platforms",
    "priority": 1
  },
  {
    "url": "https://www.criteo.com/glossary/audience-targeting/",
    "category": "Targeting",
    "description": "Audience targeting glossary",
    "priority": 1
  },
  {
    "url": "https://www.brafton.com/blog/strategy/audience-targeting-examples/",
    "category": "Targeting",
    "description": "Audience targeting examples",
    "priority": 1
  },
  {
    "url": "https://www.taboola.com/help/en/articles/10695578-audience-insights-demographics",
    "category": "Demographics",
    "description": "Audience insights demographics",
    "priority": 1
  },
  {
    "url": "https://metricswatch.com/insights/best-practices-for-social-media-demographic-reports",
    "category": "Demographics",
    "description": "Demographic reports best practices",
    "priority": 1
  },
  {
    "url": "https://improvado.io/blog/gdn-vs-dv360-ad-platform-comparison",
    "category": "Display",
    "description": "GDN vs DV360 comparison",
    "priority": 1
  },
  {
    "url": "https://www.m3.agency/news-insights/ultimate-guide-to-display-marketing-gdn-vs-dsps",
    "category": "Display",
    "description": "Display marketing guide",
    "priority": 1
  },
  {
    "url": "https://agencyanalytics.com/blog/what-is-programmatic-advertising",
    "category": "Programmatic",
    "description": "What is programmatic advertising",
    "priority": 1
  },
  {
    "url": "https://improvado.io/blog/the-trade-desk-guide",
    "category": "Programmatic",
    "description": "The Trade Desk guide",
    "priority": 1
  },
  {
    "url": "https://improvado.io/blog/looker-vs-tableau-vs-power-bi",
    "category": "Analytics",
    "description": "Looker vs Tableau vs Power BI",
    "priority": 1
  },
  {
    "url": "https://improvado.io/blog/adobe-analytics",
    "category": "Analytics",
    "description": "Adobe Analytics guide",
    "priority": 1
  },
  {
    "url": "https://improvado.io/blog/marketing-data-visualization-techniques",
    "category": "Visualization",
    "description": "Data visualization techniques",
    "priority": 1
  },
  {
    "url": "https://blog.coupler.io/data-visualization-guide/",
    "category": "Visualization",
    "description": "Data visualization guide",
    "priority": 1
  },
  {
    "url": "https://supermetrics.com/customers/shopee",
    "category": "Case Study",
    "description": "Shopee case study",
    "priority": 1
  },
  {
    "url": "https://supermetrics.com/customers/vodafoneziggo",
    "category": "Case Study",
    "description": "VodafoneZiggo case study",
    "priority": 1
  },
  {
    "url": "https://supermetrics.com/customers/pattrns",
    "category": "Case Study",
    "description": "Pattrns case study",
    "priority": 1
  },
  {
    "url": "https://supermetrics.com/customers/orange-line",
    "category": "Case Study",
    "description": "Orange Line case study",
    "priority": 1
  }
]